simphony_osp_simlammps/__init__.py
simphony_osp_simlammps/mapper.py
simphony_osp_simlammps/utils.py
simphony_osp_simlammps/wrapper.py
simphony_osp_simlammps-4.0.0.dist-info/LICENSE
simphony_osp_simlammps-4.0.0.dist-info/METADATA
simphony_osp_simlammps-4.0.0.dist-info/WHEEL
simphony_osp_simlammps-4.0.0.dist-info/entry_points.txt
simphony_osp_simlammps-4.0.0.dist-info/top_level.txt
simphony_osp_simlammps-4.0.0.dist-info/RECORD
