Metadata-Version: 2.1
Name: simphony-osp-simlammps
Version: 4.0.0
Summary: LAMMPS wrapper for SimPhoNy
Home-page: https://github.com/simphony/simlammps
Download-URL: https://pypi.org/project/simphony-osp-simlammps/4.0.0/#files
Author: Material Informatics Team, Fraunhofer IWM
Author-email: simphony@iwm.fraunhofer.de
Maintainer: Material Informatics Team, Fraunhofer IWM
Maintainer-email: simphony@iwm.fraunhofer.de
License: GPLv2
Project-URL: Tracker, https://github.com/simphony/simlammps/issues
Project-URL: Source, https://github.com/simphony/simlammps/tree/v4.0.0
Keywords: simphony,Fraunhofer IWM,LAMMPS,wrapper,simulation,molecular dynamics
Platform: any
Classifier: Development Status :: 3 - Alpha
Classifier: Intended Audience :: Science/Research
Classifier: Topic :: Scientific/Engineering
Classifier: Topic :: Scientific/Engineering :: Physics
Classifier: License :: OSI Approved :: GNU General Public License v2 (GPLv2)
Classifier: Programming Language :: Python
Classifier: Programming Language :: Python :: 3 :: Only
Classifier: Programming Language :: Python :: 3.7
Classifier: Programming Language :: Python :: 3.8
Classifier: Programming Language :: Python :: 3.9
Classifier: Programming Language :: Python :: 3.10
Classifier: Operating System :: Microsoft :: Windows
Classifier: Operating System :: MacOS
Classifier: Operating System :: Unix
Requires-Python: >=3.7
License-File: LICENSE
Requires-Dist: simphony-osp (<5.0.0rc0,>=4.0.0rc3)
Requires-Dist: numpy
